smolnet/__init__.py
smolnet/smolnet.py
smolnet/smolnet_matrix.py
smolnet-0.1.0.dist-info/METADATA
smolnet-0.1.0.dist-info/WHEEL
smolnet-0.1.0.dist-info/RECORD
