Metadata-Version: 2.1
Name: smolnet
Version: 0.1.0
Summary: smolnet, a tiny MLP module, implemented from scratch using numpy
Author: Souvik Bhattacharyya
Author-email: souvikshanku@gmail.com
Requires-Python: >=3.10,<4.0
Classifier: Programming Language :: Python :: 3
Classifier: Programming Language :: Python :: 3.10
Classifier: Programming Language :: Python :: 3.11
Requires-Dist: numpy (>=1.25.0,<2.0.0)
